aiorule34/__init__.py
aiorule34/aiorule34.py
aiorule34-1.2.0.dist-info/METADATA
aiorule34-1.2.0.dist-info/RECORD
aiorule34-1.2.0.dist-info/WHEEL
aiorule34-1.2.0.dist-info/top_level.txt
