Metadata-Version: 2.1
Name: aiorule34
Version: 1.2.0
Summary: an async wrapper for rule34.xxx
Home-page: https://github.com/Apache-HB/aiorule34
Author: Elliot Haisley
Author-email: apachehb@gmail.com
License: Apache2.0
Keywords: rule34,async,api,wrapper,porn
Platform: UNKNOWN
Requires-Dist: aiohttp
Requires-Dist: defusedxml
